pandazip/__init__.py
pandazip/pandazip.py
pandazip-0.1.0.dist-info/LICENSE
pandazip-0.1.0.dist-info/METADATA
pandazip-0.1.0.dist-info/WHEEL
pandazip-0.1.0.dist-info/top_level.txt
pandazip-0.1.0.dist-info/RECORD
