Metadata-Version: 2.1
Name: pandazip
Version: 0.1.0
Summary: Decrease DataFrame size with 2 lines of code.
Home-page: https://github.com/meetyildiz/pandazip
Author: MEHMET YILDIZ
Author-email: myildiz.ie@gmail.com
Classifier: Programming Language :: Python :: 3
Classifier: License :: OSI Approved :: MIT License
Classifier: Operating System :: OS Independent
Requires-Python: >=3.6
License-File: LICENSE
Requires-Dist: pandas
Requires-Dist: joblib
